LICENSE
MANIFEST.in
README.md
pyproject.toml
requirements.txt
setup.cfg
setup.py
dms_ci/__init__.py
dms_ci/dms_ci.py
dms_ci.egg-info/PKG-INFO
dms_ci.egg-info/SOURCES.txt
dms_ci.egg-info/dependency_links.txt
dms_ci.egg-info/requires.txt
dms_ci.egg-info/top_level.txt