Metadata-Version: 2.1
Name: dms-ci
Version: 0.2.2
Home-page: https://github.com/rouskinlab/DMS_CI
Author: Yves Martin
Author-email: yves@martin.yt
License-File: LICENSE
Requires-Dist: pandas
Requires-Dist: numpy
Requires-Dist: statsmodels
Requires-Dist: plotly
Requires-Dist: scipy
